README.md
flask_gae_static.py
setup.py
flask_gae_static.egg-info/PKG-INFO
flask_gae_static.egg-info/SOURCES.txt
flask_gae_static.egg-info/dependency_links.txt
flask_gae_static.egg-info/requires.txt
flask_gae_static.egg-info/top_level.txt
tests/__init__.py
tests/test_flask_gae_static.py