Metadata-Version: 2.1
Name: flask-gae-static
Version: 1.0
Summary: Flask extension that serves static file handlers in Google App Engine app.yaml files
Home-page: https://github.com/snarfed/flask-gae-static
Author: Ryan Barrett
Author-email: flask-gae-static@ryanb.org
License: Public domain
Keywords: flask,App Engine,Google App Engine,app.yaml,static,files,directories
Platform: UNKNOWN
Classifier: Development Status :: 5 - Production/Stable
Classifier: Intended Audience :: Developers
Classifier: Environment :: Web Environment
Classifier: License :: OSI Approved :: MIT License
Classifier: License :: Public Domain
Classifier: Programming Language :: Python :: 3
Classifier: Programming Language :: Python :: 3.6
Classifier: Programming Language :: Python :: 3.7
Classifier: Programming Language :: Python :: 3.8
Classifier: Programming Language :: Python :: 3.9
Classifier: Topic :: Software Development :: Libraries :: Python Modules
Classifier: Framework :: Flask
Requires-Python: >=3.6
